CHANGELOG.txt
LICENSE.txt
MANIFEST.in
README.md
setup.py
kalkulatorsd/__init__.py
kalkulatorsd.egg-info/PKG-INFO
kalkulatorsd.egg-info/SOURCES.txt
kalkulatorsd.egg-info/dependency_links.txt
kalkulatorsd.egg-info/top_level.txt